jupyter_native_kernel/__init__.py
jupyter_native_kernel/__main__.py
jupyter_native_kernel/install_native_kernel.py
jupyter_native_kernel/kernel.py
jupyter_native_kernel/resources/master.c
jupyter_native_kernel-0.0.9.dist-info/LICENSE
jupyter_native_kernel-0.0.9.dist-info/METADATA
jupyter_native_kernel-0.0.9.dist-info/WHEEL
jupyter_native_kernel-0.0.9.dist-info/entry_points.txt
jupyter_native_kernel-0.0.9.dist-info/top_level.txt
jupyter_native_kernel-0.0.9.dist-info/RECORD
