Metadata-Version: 2.1
Name: jupyter-native-kernel
Version: 0.0.9
Summary: A minimalistic Jupyter kernel for native code execution.
Author-email: UNCC HPCAS Lab <yyan7@uncc.edu>
License: The MIT License (MIT)
Project-URL: Homepage, https://passlab.github.io
Project-URL: Repository, https://github.com/passlab/jupyter-native-kernel.git
Project-URL: Issues, https://github.com/passlab/jupyter-native-kernel/issues
Classifier: Programming Language :: Python :: 3
Classifier: License :: OSI Approved :: MIT License
Classifier: Operating System :: OS Independent
Requires-Python: >=3.8
License-File: LICENSE
Requires-Dist: jupyterlab>=4.3
Requires-Dist: openai>=1.58
